<?xml version="1.0" encoding="UTF-8"?><database>
    <element db_object_id="76cdde5b60f902107f44b4f7aba5bdc2" label="Orders" max_length="40" name="x_cdltd_dropship_0_orders" type="collection">
        <element label="City" max_length="40" name="city" type="string"/>
        <element label="Email Address" max_length="40" name="email_address" type="string"/>
        <element attributes="edge_encryption_enabled=true" default="javascript:global.getNextObjNumberPadded();" label="Order ID" max_length="40" name="number" type="string"/>
        <element active="false" label="Shipping Address" max_length="40" name="shipping_address" type="string"/>
        <element label="State" max_length="40" name="state" type="string"/>
        <element choice="1" label="Status" max_length="40" name="status" type="choice">
            <choice>
                <element inactive_on_update="false" label="Pre-Checkout" sequence="0" value="pre_checkout"/>
                <element inactive_on_update="false" label="Processing" sequence="1" value="processing"/>
                <element inactive_on_update="false" label="Shipped" sequence="2" value="shipped"/>
            </choice>
        </element>
        <element label="Street Address" max_length="40" name="street_address" type="string"/>
        <element default="javascript:current.getTableName();" label="Class" max_length="80" name="sys_class_name" type="sys_class_name"/>
        <element label="TotalAmount" max_length="40" name="totalamount" type="decimal"/>
        <element label="Zip Code" max_length="40" name="zip_code" type="string"/>
        <index name="index">
            <element name="sys_class_name"/>
        </index>
    </element>
</database>
